openrte/__init__.py
openrte/client.py
openrte/retriever.py
openrte/tools.py
openrte-1.0.1.dist-info/licenses/LICENSE
openrte-1.0.1.dist-info/METADATA
openrte-1.0.1.dist-info/WHEEL
openrte-1.0.1.dist-info/top_level.txt
openrte-1.0.1.dist-info/RECORD
